onecomic/__init__.py
onecomic/__main__.py
onecomic/cli.py
onecomic/comicbook.py
onecomic/config.py
onecomic/crawlerbase.py
onecomic/exceptions.py
onecomic/image.py
onecomic/migrate.py
onecomic/patch.py
onecomic/session.py
onecomic/worker.py
onecomic/js/cocomanhua.js
onecomic/js/laimanhua_base64.js
onecomic/proxy/__init__.py
onecomic/proxy/kuaidaili.py
onecomic/site/__init__.py
onecomic/site/acg456.py
onecomic/site/baozimh.py
onecomic/site/bilibili.py
onecomic/site/boodo.py
onecomic/site/boylove.py
onecomic/site/c177pic.py
onecomic/site/c18comic.py
onecomic/site/c18hmmcg.py
onecomic/site/c2animx.py
onecomic/site/c2feimh.py
onecomic/site/c3250mh.py
onecomic/site/c36mh.py
onecomic/site/c55comic.py
onecomic/site/c77mh.py
onecomic/site/cocomanhua.py
onecomic/site/copymanga.py
onecomic/site/dm5.py
onecomic/site/dmzj.py
onecomic/site/gufengmh.py
onecomic/site/iqiyi.py
onecomic/site/jmzj.py
onecomic/site/kanman.py
onecomic/site/kuaikan.py
onecomic/site/kuimh.py
onecomic/site/laimanhua.py
onecomic/site/manhuadb.py
onecomic/site/manhuafei.py
onecomic/site/manhuagui.py
onecomic/site/manhuatai.py
onecomic/site/manwa.py
onecomic/site/mh1234.py
onecomic/site/mh160.py
onecomic/site/mmkk.py
onecomic/site/myfcomic.py
onecomic/site/nhentai.py
onecomic/site/nsfwpicx.py
onecomic/site/nvshens.py
onecomic/site/pufei8.py
onecomic/site/qiman6.py
onecomic/site/qimiaomh.py
onecomic/site/qootoon.py
onecomic/site/qq.py
onecomic/site/sixmh6.py
onecomic/site/toomics.py
onecomic/site/tuhao456.py
onecomic/site/twhentai.py
onecomic/site/u17.py
onecomic/site/webtoons.py
onecomic/site/wnacg.py
onecomic/site/xiuren.py
onecomic/site/ykmh.py
onecomic/site/yymh889.py
onecomic/utils/__init__.py
onecomic/utils/_img2pdf.py
onecomic/utils/mail.py
onecomic-0.2.55.data/scripts/onecomic
onecomic-0.2.55.dist-info/LICENSE
onecomic-0.2.55.dist-info/METADATA
onecomic-0.2.55.dist-info/WHEEL
onecomic-0.2.55.dist-info/top_level.txt
onecomic-0.2.55.dist-info/RECORD
