Metadata-Version: 2.1
Name: onecomic
Version: 0.2.55
Summary: onecomic
Home-page: https://github.com/hardwarecode/onecomic
Author: hardwarecode
Author-email: 
License: GPL-3.0 License
Classifier: License :: OSI Approved :: GNU General Public License v3 (GPLv3)
Classifier: Programming Language :: Python
Classifier: Programming Language :: Python :: 3
Classifier: Programming Language :: Python :: 3.6
Classifier: Programming Language :: Python :: Implementation :: CPython
Classifier: Programming Language :: Python :: Implementation :: PyPy
Requires-Python: >=3.6
License-File: LICENSE
Requires-Dist: Pillow >=6.2.0
Requires-Dist: PyExecJS ==1.5.1
Requires-Dist: bs4 ==0.0.1
Requires-Dist: jsbeautifier
Requires-Dist: lzstring >=1.0.4
Requires-Dist: hyper >=0.7.0
Requires-Dist: httpx >=0.23.0
Requires-Dist: httpx-socks >=0.7.4
Requires-Dist: PySocks >=1.7.1
Requires-Dist: pycryptodomex >=3.18.0
Requires-Dist: chardet >=5.2.0
